LICENSE.md
MANIFEST.in
README.md
requirements.txt
setup.py
cvutils/__init__.py
cvutils/writing.py
opencv_utils.egg-info/PKG-INFO
opencv_utils.egg-info/SOURCES.txt
opencv_utils.egg-info/dependency_links.txt
opencv_utils.egg-info/top_level.txt