Metadata-Version: 1.0
Name: opencv-utils
Version: 0.0.2
Summary: OpenCV Utilities
Home-page: https://github.com/shubhamchaudhary/opencv-utils
Author: Shubham Chaudhary
Author-email: me@shubhamchaudhary.in
License: GPLv3+
Platform: UNKNOWN
